pykeycloakutils/__init__.py
pykeycloakutils/_decorators.py
py_keycloak_utils-1.0.4.dist-info/METADATA
py_keycloak_utils-1.0.4.dist-info/WHEEL
py_keycloak_utils-1.0.4.dist-info/top_level.txt
py_keycloak_utils-1.0.4.dist-info/RECORD
