Metadata-Version: 2.1
Name: py-keycloak-utils
Version: 1.0.4
Summary: Utilities with Keycloak
Author: KE
Author-email: 
Keywords: python,flask,PyJWT,decorator,token,keycloak
Classifier: Development Status :: 1 - Planning
Classifier: Intended Audience :: Developers
Classifier: Programming Language :: Python :: 3.11
Classifier: Operating System :: Unix
Classifier: Operating System :: MacOS
Requires-Dist: flask (<=2.2.3,>=2.0.0)
Requires-Dist: python-keycloak (==3.3.0)
